volmemlyzer/__init__.py
volmemlyzer/analysis.py
volmemlyzer/cli.py
volmemlyzer/converters.py
volmemlyzer/core.py
volmemlyzer/extractor_registry.py
volmemlyzer/extractors.py
volmemlyzer/pipeline.py
volmemlyzer/plugins.py
volmemlyzer/runner.py
volmemlyzer/terminalUI.py
volmemlyzer/utilities.py
volmemlyzer-3.0.1.dist-info/licenses/LICENSE
volmemlyzer-3.0.1.dist-info/METADATA
volmemlyzer-3.0.1.dist-info/WHEEL
volmemlyzer-3.0.1.dist-info/entry_points.txt
volmemlyzer-3.0.1.dist-info/top_level.txt
volmemlyzer-3.0.1.dist-info/RECORD
