Metadata-Version: 2.4
Name: volmemlyzer
Version: 3.0.1
Summary: Volatility 3-powered memory forensics: parallel plugin runs, DFIR analysis, and ML-ready features.
Author-email: Yasin Dehfouli <yasind@yorku.ca>
License:                     GNU GENERAL PUBLIC LICENSE
Project-URL: Homepage, https://github.com/ahlashkari/VolMemLyzer
Project-URL: Issues, https://github.com/ahlashkari/VolMemLyzer/issues
Keywords: volatility,forensics,dfir,memory,malware,security
Classifier: Development Status :: 4 - Beta
Classifier: Intended Audience :: Science/Research
Classifier: Topic :: Security
Classifier: License :: OSI Approved :: GNU General Public License v3 or later (GPLv3+)
Classifier: Programming Language :: Python :: 3
Classifier: Programming Language :: Python :: 3.9
Classifier: Programming Language :: Python :: 3.10
Classifier: Programming Language :: Python :: 3.11
Classifier: Programming Language :: Python :: 3.12
Requires-Python: >=3.9
License-File: LICENSE
Requires-Dist: volatility3
Requires-Dist: pandas>=2.0.0
Requires-Dist: numpy>=1.24.0
Requires-Dist: python-dateutil>=2.8.2
Requires-Dist: tqdm>=4.65.0
Requires-Dist: rich>=13.3.0
Dynamic: license-file
